pykwb/__init__.py
pykwb/kwb.py
pykwb-0.0.9.dist-info/DESCRIPTION.rst
pykwb-0.0.9.dist-info/METADATA
pykwb-0.0.9.dist-info/RECORD
pykwb-0.0.9.dist-info/WHEEL
pykwb-0.0.9.dist-info/metadata.json
pykwb-0.0.9.dist-info/top_level.txt
